{
  "$schema": "../../../packages/schema-engine/meta-schemas/vocabulary.schema.json",
  "id": "location-subtypes",
  "schema_version": 1,
  "values": {
    "ocean": { "labels": { "en": "Ocean", "fr": "Océan" } },
    "sea": { "labels": { "en": "Sea", "fr": "Mer" } },
    "island": { "labels": { "en": "Island", "fr": "Île" } },
    "archipelago": { "labels": { "en": "Archipelago", "fr": "Archipel" } },
    "kingdom": { "labels": { "en": "Kingdom", "fr": "Royaume" } },
    "country": { "labels": { "en": "Country", "fr": "Pays" } },
    "city": { "labels": { "en": "City", "fr": "Ville" } },
    "town": { "labels": { "en": "Town", "fr": "Bourg" } },
    "village": { "labels": { "en": "Village", "fr": "Village" } },
    "region": { "labels": { "en": "Region", "fr": "Région" } },
    "building": { "labels": { "en": "Building", "fr": "Bâtiment" } },
    "sky_island": { "labels": { "en": "Sky island", "fr": "Île céleste" } },
    "undersea": { "labels": { "en": "Undersea", "fr": "Sous-marin" } },
    "fishman_district": {
      "labels": { "en": "Fishman district", "fr": "Quartier des hommes-poissons" }
    },
    "ghost_island": { "labels": { "en": "Ghost island", "fr": "Île fantôme" } },
    "floating_island": { "labels": { "en": "Floating island", "fr": "Île flottante" } },
    "pirate_haven": { "labels": { "en": "Pirate haven", "fr": "Repaire pirate" } },
    "marine_base": { "labels": { "en": "Marine base", "fr": "Base de la Marine" } },
    "prison": { "labels": { "en": "Prison", "fr": "Prison" } }
  }
}
